mylib_516/__init__.py
mylib_516-0.1.dist-info/LICENSE.txt
mylib_516-0.1.dist-info/METADATA
mylib_516-0.1.dist-info/WHEEL
mylib_516-0.1.dist-info/top_level.txt
mylib_516-0.1.dist-info/RECORD
