Metadata-Version: 2.1
Name: mylib-516
Version: 0.1
Summary: calculating cube
Home-page: UNKNOWN
Author: Hritik
Author-email: hkdjmore@gmail.com
License: UNKNOWN
Platform: UNKNOWN
Classifier: Programming Language :: Python :: 3
Classifier: License :: OSI Approved :: MIT License
Classifier: Operating System :: OS Independent
License-File: LICENSE.txt
